yapx/__init__.py
yapx/__version__.py
yapx/actions.py
yapx/arg.py
yapx/argument_parser.py
yapx/command.py
yapx/context.py
yapx/exceptions.py
yapx/namespace.py
yapx/py.typed
yapx/types.py
yapx/utils.py
yapx/__pycache__/__init__.cpython-310.pyc
yapx/__pycache__/__version__.cpython-310.pyc
yapx/__pycache__/actions.cpython-310.pyc
yapx/__pycache__/arg.cpython-310.pyc
yapx/__pycache__/argument_parser.cpython-310.pyc
yapx/__pycache__/command.cpython-310.pyc
yapx/__pycache__/context.cpython-310.pyc
yapx/__pycache__/exceptions.cpython-310.pyc
yapx/__pycache__/namespace.cpython-310.pyc
yapx/__pycache__/types.cpython-310.pyc
yapx/__pycache__/utils.cpython-310.pyc
yapx-0.5.2.dist-info/LICENSE
yapx-0.5.2.dist-info/METADATA
yapx-0.5.2.dist-info/WHEEL
yapx-0.5.2.dist-info/top_level.txt
yapx-0.5.2.dist-info/RECORD
