Metadata-Version: 2.1
Name: yapx
Version: 0.5.2
Summary: The next generation of Python's Argparse.
Author-email: Donald Mellenbruch <hello@f2dv.com>
License: Copyright 2023 Donald Mellenbruch
Project-URL: Homepage, https://www.f2dv.com/r/yapx
Project-URL: Repository, https://www.github.com/fresh2dev/yapx
Classifier: Programming Language :: Python :: 3
Requires-Python: >=3.7
License-File: LICENSE
Requires-Dist: typing-extensions ; python_version < "3.10"
Requires-Dist: importlib-metadata ; python_version < "3.8"
Provides-Extra: dev
Requires-Dist: pdbpp ; extra == 'dev'
Requires-Dist: ipykernel ; extra == 'dev'
Requires-Dist: ipywidgets ; extra == 'dev'
Requires-Dist: ipython ; extra == 'dev'
Provides-Extra: extras
Requires-Dist: pydantic <3,>=1.10.3 ; extra == 'extras'
Requires-Dist: shtab ==1.6.2 ; extra == 'extras'
Requires-Dist: rich-argparse ==1.* ; extra == 'extras'
Requires-Dist: pyyaml <7,>=5 ; extra == 'extras'
Requires-Dist: argparse-tui <1,>=0.2.2 ; extra == 'extras'
Provides-Extra: pydantic
Requires-Dist: pydantic <3,>=1.10.3 ; extra == 'pydantic'
Provides-Extra: rich
Requires-Dist: rich-argparse ==1.* ; extra == 'rich'
Provides-Extra: shtab
Requires-Dist: shtab ==1.6.* ; extra == 'shtab'
Provides-Extra: tests
Requires-Dist: pytest ==7.* ; extra == 'tests'
Requires-Dist: pytest-cov ==4.* ; extra == 'tests'
Requires-Dist: pytest-html ==3.* ; extra == 'tests'
Requires-Dist: pytest-sugar ==0.* ; extra == 'tests'
Requires-Dist: pytest-custom-exit-code ==0.3.* ; extra == 'tests'
Requires-Dist: packaging ==23.* ; extra == 'tests'
Requires-Dist: pydantic <3,>=1.10.3 ; extra == 'tests'
Requires-Dist: shtab ==1.6.* ; extra == 'tests'
Requires-Dist: rich-argparse ==1.* ; extra == 'tests'
Requires-Dist: pyyaml <7,>=5 ; extra == 'tests'
Provides-Extra: tui
Requires-Dist: argparse-tui <1,>=0.2.1 ; extra == 'tui'
Provides-Extra: yaml
Requires-Dist: pyyaml <7,>=5 ; extra == 'yaml'
